nonebot_plugin_game_collection/__init__.py
nonebot_plugin_game_collection-4.0.0.dist-info/LICENSE
nonebot_plugin_game_collection-4.0.0.dist-info/METADATA
nonebot_plugin_game_collection-4.0.0.dist-info/WHEEL
nonebot_plugin_game_collection-4.0.0.dist-info/RECORD
