Metadata-Version: 2.3
Name: nonebot-plugin-game-collection
Version: 4.0.0
Summary: 
Author: KarisAya
Author-email: 1048827424@qq.com
Requires-Python: >=3.12,<4.0.0
Classifier: Programming Language :: Python :: 3
Classifier: Programming Language :: Python :: 3.12
Classifier: Programming Language :: Python :: 3.13
Requires-Dist: clovers-sarof (>=0.1.0,<0.2.0)
Requires-Dist: clovers-sarof-account (>=0.1.0,<0.2.0)
Requires-Dist: clovers-sarof-gacha (>=0.1.0,<0.2.0)
Requires-Dist: clovers-sarof-game-collection (>=0.1.0,<0.2.0)
Requires-Dist: clovers-sarof-market (>=0.1.0,<0.2.0)
Requires-Dist: clovers-sarof-ranklist (>=0.1.0,<0.2.0)
Requires-Dist: nonebot-plugin-clovers (>=0.3.5,<0.4.0)
Requires-Dist: nonebot2 (>=2.4.2,<3.0.0)
